<?xml version="1.0" encoding="UTF-8"?>
<CityValueSet>
  <CityItem>
    <CityId>201</CityId>
    <CityName>北京</CityName>
    <EngName>beijing</EngName>
    <Level>1</Level>
    <ParentId>2</ParentId>
    <Memo1>201</Memo1>
    <Memo2>1</Memo2>
    <Memo3>
    </Memo3>
  </CityItem>
  <CityItem>
    <CityId>2601</CityId>
    <CityName>天津</CityName>
    <EngName>tianjin</EngName>
    <Level>1</Level>
    <ParentId>26</ParentId>
    <Memo1>2601</Memo1>
    <Memo2>3</Memo2>
    <Memo3>
    </Memo3>
  </CityItem>
  <CityItem>
    <CityId>901</CityId>
    <CityName>石家庄</CityName>
    <EngName>shijiazhuang</EngName>
    <Level>1</Level>
    <ParentId>9</ParentId>
    <Memo1>901</Memo1>
    <Memo2>6</Memo2>
    <Memo3>
    </Memo3>
  </CityItem>
  <CityItem>
    <CityId>1101</CityId>
    <CityName>哈尔滨</CityName>
    <EngName>haerbin</EngName>
    <Level>1</Level>
    <ParentId>11</ParentId>
    <Memo1>1101</Memo1>
    <Memo2>11</Memo2>
    <Memo3>
    </Memo3>
  </CityItem>
  <CityItem>
    <CityId>1401</CityId>
    <CityName>长春</CityName>
    <EngName>changchun</EngName>
    <Level>1</Level>
    <ParentId>14</ParentId>
    <Memo1>1401</Memo1>
    <Memo2>8</Memo2>
    <Memo3>
    </Memo3>
  </CityItem>
  <CityItem>
    <CityId>1701</CityId>
    <CityName>沈阳</CityName>
    <EngName>shenyang</EngName>
    <Level>1</Level>
    <ParentId>17</ParentId>
    <Memo1>1701</Memo1>
    <Memo2>9</Memo2>
    <Memo3>
    </Memo3>
  </CityItem>
  <CityItem>
    <CityId>1708</CityId>
    <CityName>大连</CityName>
    <EngName>dalian</EngName>
    <Level>2</Level>
    <ParentId>17</ParentId>
    <Memo1>1708</Memo1>
    <Memo2>10</Memo2>
    <Memo3>
    </Memo3>
  </CityItem>
  <CityItem>
    <CityId>1801</CityId>
    <CityName>呼和浩特</CityName>
    <EngName>huhehaote</EngName>
    <Level>2</Level>
    <ParentId>18</ParentId>
    <Memo1>1801</Memo1>
    <Memo2>2</Memo2>
    <Memo3>
    </Memo3>
  </CityItem>
  <CityItem>
    <CityId>2101</CityId>
    <CityName>济南</CityName>
    <EngName>jinan</EngName>
    <Level>1</Level>
    <ParentId>21</ParentId>
    <Memo1>2101</Memo1>
    <Memo2>4</Memo2>
    <Memo3>
    </Memo3>
  </CityItem>
  <CityItem>
    <CityId>2102</CityId>
    <CityName>青岛</CityName>
    <EngName>qingdao</EngName>
    <Level>1</Level>
    <ParentId>21</ParentId>
    <Memo1>2102</Memo1>
    <Memo2>5</Memo2>
    <Memo3>
    </Memo3>
  </CityItem>
  <CityItem>
    <CityId>2201</CityId>
    <CityName>太原</CityName>
    <EngName>taiyuan</EngName>
    <Level>1</Level>
    <ParentId>22</ParentId>
    <Memo1>2201</Memo1>
    <Memo2>7</Memo2>
    <Memo3>
    </Memo3>
  </CityItem>
  <CityItem>
    <CityId>1001</CityId>
    <CityName>郑州</CityName>
    <EngName>zhengzhou</EngName>
    <Level>1</Level>
    <ParentId>10</ParentId>
    <Memo1>1001</Memo1>
    <Memo2>23</Memo2>
    <Memo3>
    </Memo3>
  </CityItem>
  <CityItem>
    <CityId>1201</CityId>
    <CityName>武汉</CityName>
    <EngName>wuhan</EngName>
    <Level>1</Level>
    <ParentId>12</ParentId>
    <Memo1>1201</Memo1>
    <Memo2>21</Memo2>
    <Memo3>
    </Memo3>
  </CityItem>
  <CityItem>
    <CityId>1301</CityId>
    <CityName>长沙</CityName>
    <EngName>changsha</EngName>
    <Level>1</Level>
    <ParentId>13</ParentId>
    <Memo1>1301</Memo1>
    <Memo2>24</Memo2>
    <Memo3>
    </Memo3>
  </CityItem>
  <CityItem>
    <CityId>1601</CityId>
    <CityName>南昌</CityName>
    <EngName>nanchang</EngName>
    <Level>2</Level>
    <ParentId>16</ParentId>
    <Memo1>1601</Memo1>
    <Memo2>22</Memo2>
    <Memo3>
    </Memo3>
  </CityItem>
  <CityItem>
    <CityId>502</CityId>
    <CityName>深圳</CityName>
    <EngName>shenzhen</EngName>
    <Level>1</Level>
    <ParentId>5</ParentId>
    <Memo1>502</Memo1>
    <Memo2>19</Memo2>
    <Memo3>
    </Memo3>
  </CityItem>
  <CityItem>
    <CityId>501</CityId>
    <CityName>广州</CityName>
    <EngName>guangzhou</EngName>
    <Level>1</Level>
    <ParentId>5</ParentId>
    <Memo1>501</Memo1>
    <Memo2>20</Memo2>
    <Memo3>
    </Memo3>
  </CityItem>
  <CityItem>
    <CityId>601</CityId>
    <CityName>南宁</CityName>
    <EngName>nanning</EngName>
    <Level>2</Level>
    <ParentId>6</ParentId>
    <Memo1>601</Memo1>
    <Memo2>116</Memo2>
    <Memo3>
    </Memo3>
  </CityItem>
  <CityItem>
    <CityId>301</CityId>
    <CityName>福州</CityName>
    <EngName>fuzhou</EngName>
    <Level>1</Level>
    <ParentId>3</ParentId>
    <Memo1>301</Memo1>
    <Memo2>18</Memo2>
    <Memo3>
    </Memo3>
  </CityItem>
  <CityItem>
    <CityId>2401</CityId>
    <CityName>上海</CityName>
    <EngName>shanghai</EngName>
    <Level>1</Level>
    <ParentId>24</ParentId>
    <Memo1>2401</Memo1>
    <Memo2>12</Memo2>
    <Memo3>
    </Memo3>
  </CityItem>
  <CityItem>
    <CityId>3001</CityId>
    <CityName>杭州</CityName>
    <EngName>hangzhou</EngName>
    <Level>1</Level>
    <ParentId>30</ParentId>
    <Memo1>3001</Memo1>
    <Memo2>16</Memo2>
    <Memo3>
    </Memo3>
  </CityItem>
  <CityItem>
    <CityId>3002</CityId>
    <CityName>宁波</CityName>
    <EngName>ningbo</EngName>
    <Level>2</Level>
    <ParentId>30</ParentId>
    <Memo1>3002</Memo1>
    <Memo2>17</Memo2>
    <Memo3>
    </Memo3>
  </CityItem>
  <CityItem>
    <CityId>101</CityId>
    <CityName>合肥</CityName>
    <EngName>hefei</EngName>
    <Level>2</Level>
    <ParentId>1</ParentId>
    <Memo1>101</Memo1>
    <Memo2>13</Memo2>
    <Memo3>
    </Memo3>
  </CityItem>
  <CityItem>
    <CityId>1502</CityId>
    <CityName>苏州</CityName>
    <EngName>suzhou</EngName>
    <Level>2</Level>
    <ParentId>15</ParentId>
    <Memo1>1502</Memo1>
    <Memo2>15</Memo2>
    <Memo3>
    </Memo3>
  </CityItem>
  <CityItem>
    <CityId>1501</CityId>
    <CityName>南京</CityName>
    <EngName>nanjing</EngName>
    <Level>1</Level>
    <ParentId>15</ParentId>
    <Memo1>1501</Memo1>
    <Memo2>14</Memo2>
    <Memo3>
    </Memo3>
  </CityItem>
  <CityItem>
    <CityId>3101</CityId>
    <CityName>重庆</CityName>
    <EngName>chongqing</EngName>
    <Level>1</Level>
    <ParentId>31</ParentId>
    <Memo1>3101</Memo1>
    <Memo2>26</Memo2>
    <Memo3>
    </Memo3>
  </CityItem>
  <CityItem>
    <CityId>2301</CityId>
    <CityName>西安</CityName>
    <EngName>xian</EngName>
    <Level>1</Level>
    <ParentId>23</ParentId>
    <Memo1>2301</Memo1>
    <Memo2>28</Memo2>
    <Memo3>
    </Memo3>
  </CityItem>
  <CityItem>
    <CityId>401</CityId>
    <CityName>兰州</CityName>
    <EngName>lanzhou</EngName>
    <Level>2</Level>
    <ParentId>4</ParentId>
    <Memo1>401</Memo1>
    <Memo2>29</Memo2>
    <Memo3>
    </Memo3>
  </CityItem>
  <CityItem>
    <CityId>2501</CityId>
    <CityName>成都</CityName>
    <EngName>chengdu</EngName>
    <Level>1</Level>
    <ParentId>25</ParentId>
    <Memo1>2501</Memo1>
    <Memo2>25</Memo2>
    <Memo3>
    </Memo3>
  </CityItem>
  <CityItem>
    <CityId>2901</CityId>
    <CityName>昆明</CityName>
    <EngName>kunming</EngName>
    <Level>2</Level>
    <ParentId>29</ParentId>
    <Memo1>2901</Memo1>
    <Memo2>27</Memo2>
    <Memo3>
    </Memo3>
  </CityItem>
  <CityItem>
    <CityId>902</CityId>
    <CityName>唐山</CityName>
    <EngName>tangshan</EngName>
    <Level>2</Level>
    <ParentId>9</ParentId>
    <Memo1>901</Memo1>
    <Memo2>49</Memo2>
    <Memo3>
    </Memo3>
  </CityItem>
  <CityItem>
    <CityId>910</CityId>
    <CityName>保定</CityName>
    <EngName>baoding</EngName>
    <Level>2</Level>
    <ParentId>9</ParentId>
    <Memo1>901</Memo1>
    <Memo2>50</Memo2>
    <Memo3>
    </Memo3>
  </CityItem>
  <CityItem>
    <CityId>2117</CityId>
    <CityName>临沂</CityName>
    <EngName>linyi</EngName>
    <Level>3</Level>
    <ParentId>21</ParentId>
    <Memo1>2101</Memo1>
    <Memo2>35</Memo2>
    <Memo3>
    </Memo3>
  </CityItem>
  <CityItem>
    <CityId>2109</CityId>
    <CityName>淄博</CityName>
    <EngName>zibo</EngName>
    <Level>2</Level>
    <ParentId>21</ParentId>
    <Memo1>2101</Memo1>
    <Memo2>34</Memo2>
    <Memo3>
    </Memo3>
  </CityItem>
  <CityItem>
    <CityId>2103</CityId>
    <CityName>烟台</CityName>
    <EngName>yantai</EngName>
    <Level>2</Level>
    <ParentId>21</ParentId>
    <Memo1>2102</Memo1>
    <Memo2>45</Memo2>
    <Memo3>
    </Memo3>
  </CityItem>
  <CityItem>
    <CityId>2105</CityId>
    <CityName>潍坊</CityName>
    <EngName>weifang</EngName>
    <Level>3</Level>
    <ParentId>21</ParentId>
    <Memo1>2102</Memo1>
    <Memo2>46</Memo2>
    <Memo3>
    </Memo3>
  </CityItem>
  <CityItem>
    <CityId>1002</CityId>
    <CityName>洛阳</CityName>
    <EngName>luoyang</EngName>
    <Level>2</Level>
    <ParentId>10</ParentId>
    <Memo1>1001</Memo1>
    <Memo2>125</Memo2>
    <Memo3>
    </Memo3>
  </CityItem>
  <CityItem>
    <CityId>505</CityId>
    <CityName>中山</CityName>
    <EngName>zhongshan</EngName>
    <Level>3</Level>
    <ParentId>5</ParentId>
    <Memo1>502</Memo1>
    <Memo2>104</Memo2>
    <Memo3>
    </Memo3>
  </CityItem>
  <CityItem>
    <CityId>518</CityId>
    <CityName>佛山</CityName>
    <EngName>foshan</EngName>
    <Level>2</Level>
    <ParentId>5</ParentId>
    <Memo1>501</Memo1>
    <Memo2>107</Memo2>
    <Memo3>
    </Memo3>
  </CityItem>
  <CityItem>
    <CityId>504</CityId>
    <CityName>东莞</CityName>
    <EngName>dongguan</EngName>
    <Level>2</Level>
    <ParentId>5</ParentId>
    <Memo1>501</Memo1>
    <Memo2>106</Memo2>
    <Memo3>
    </Memo3>
  </CityItem>
  <CityItem>
    <CityId>801</CityId>
    <CityName>海口</CityName>
    <EngName>haikou</EngName>
    <Level>2</Level>
    <ParentId>8</ParentId>
    <Memo1>501</Memo1>
    <Memo2>115</Memo2>
    <Memo3>
    </Memo3>
  </CityItem>
  <CityItem>
    <CityId>602</CityId>
    <CityName>柳州</CityName>
    <EngName>liuzhou</EngName>
    <Level>5</Level>
    <ParentId>6</ParentId>
    <Memo1>601</Memo1>
    <Memo2>117</Memo2>
    <Memo3>
    </Memo3>
  </CityItem>
  <CityItem>
    <CityId>302</CityId>
    <CityName>厦门</CityName>
    <EngName>xiamen</EngName>
    <Level>2</Level>
    <ParentId>3</ParentId>
    <Memo1>301</Memo1>
    <Memo2>97</Memo2>
    <Memo3>
    </Memo3>
  </CityItem>
  <CityItem>
    <CityId>307</CityId>
    <CityName>泉州</CityName>
    <EngName>quanzhou</EngName>
    <Level>2</Level>
    <ParentId>3</ParentId>
    <Memo1>301</Memo1>
    <Memo2>98</Memo2>
    <Memo3>
    </Memo3>
  </CityItem>
  <CityItem>
    <CityId>3006</CityId>
    <CityName>金华</CityName>
    <EngName>jinhua</EngName>
    <Level>2</Level>
    <ParentId>30</ParentId>
    <Memo1>3001</Memo1>
    <Memo2>93</Memo2>
    <Memo3>
    </Memo3>
  </CityItem>
  <CityItem>
    <CityId>3016</CityId>
    <CityName>绍兴</CityName>
    <EngName>shaoxing</EngName>
    <Level>3</Level>
    <ParentId>30</ParentId>
    <Memo1>3001</Memo1>
    <Memo2>91</Memo2>
    <Memo3>
    </Memo3>
  </CityItem>
  <CityItem>
    <CityId>3003</CityId>
    <CityName>温州</CityName>
    <EngName>wenzhou</EngName>
    <Level>2</Level>
    <ParentId>30</ParentId>
    <Memo1>3001</Memo1>
    <Memo2>89</Memo2>
    <Memo3>
    </Memo3>
  </CityItem>
  <CityItem>
    <CityId>3015</CityId>
    <CityName>台州</CityName>
    <EngName>tz</EngName>
    <Level>3</Level>
    <ParentId>30</ParentId>
    <Memo1>3001</Memo1>
    <Memo2>90</Memo2>
    <Memo3>
    </Memo3>
  </CityItem>
  <CityItem>
    <CityId>1518</CityId>
    <CityName>徐州</CityName>
    <EngName>xuzhou</EngName>
    <Level>2</Level>
    <ParentId>15</ParentId>
    <Memo1>1501</Memo1>
    <Memo2>81</Memo2>
    <Memo3>
    </Memo3>
  </CityItem>
  <CityItem>
    <CityId>1503</CityId>
    <CityName>无锡</CityName>
    <EngName>wuxi</EngName>
    <Level>2</Level>
    <ParentId>15</ParentId>
    <Memo1>1502</Memo1>
    <Memo2>85</Memo2>
    <Memo3>
    </Memo3>
  </CityItem>
  <CityItem>
    <CityId>1511</CityId>
    <CityName>南通</CityName>
    <EngName>nantong</EngName>
    <Level>3</Level>
    <ParentId>15</ParentId>
    <Memo1>1501</Memo1>
    <Memo2>80</Memo2>
    <Memo3>
    </Memo3>
  </CityItem>
  <CityItem>
    <CityId>1505</CityId>
    <CityName>常州</CityName>
    <EngName>changzhou</EngName>
    <Level>3</Level>
    <ParentId>15</ParentId>
    <Memo1>1501</Memo1>
    <Memo2>79</Memo2>
    <Memo3>
    </Memo3>
  </CityItem>
  <CityItem>
    <CityId>1901</CityId>
    <CityName>银川</CityName>
    <EngName>yinchuan</EngName>
    <Level>2</Level>
    <ParentId>19</ParentId>
    <Memo1>401</Memo1>
    <Memo2>162</Memo2>
    <Memo3>
    </Memo3>
  </CityItem>
  <CityItem>
    <CityId>2801</CityId>
    <CityName>乌鲁木齐</CityName>
    <EngName>wulumuqi</EngName>
    <Level>2</Level>
    <ParentId>28</ParentId>
    <Memo1>401</Memo1>
    <Memo2>152</Memo2>
    <Memo3>
    </Memo3>
  </CityItem>
  <CityItem>
    <CityId>701</CityId>
    <CityName>贵阳</CityName>
    <EngName>guiyang</EngName>
    <Level>2</Level>
    <ParentId>7</ParentId>
    <Memo1>2901</Memo1>
    <Memo2>145</Memo2>
    <Memo3>
    </Memo3>
  </CityItem>
  <CityItem>
    <CityId>903</CityId>
    <CityName>邢台</CityName>
    <EngName>xingtai</EngName>
    <Level>4</Level>
    <ParentId>9</ParentId>
    <Memo1>901</Memo1>
    <Memo2>53</Memo2>
    <Memo3>
    </Memo3>
  </CityItem>
  <CityItem>
    <CityId>907</CityId>
    <CityName>邯郸</CityName>
    <EngName>handan</EngName>
    <Level>4</Level>
    <ParentId>9</ParentId>
    <Memo1>901</Memo1>
    <Memo2>51</Memo2>
    <Memo3>
    </Memo3>
  </CityItem>
  <CityItem>
    <CityId>909</CityId>
    <CityName>沧州</CityName>
    <EngName>cangzhou</EngName>
    <Level>4</Level>
    <ParentId>9</ParentId>
    <Memo1>901</Memo1>
    <Memo2>52</Memo2>
    <Memo3>
    </Memo3>
  </CityItem>
  <CityItem>
    <CityId>905</CityId>
    <CityName>秦皇岛</CityName>
    <EngName>qinhuangdao</EngName>
    <Level>4</Level>
    <ParentId>9</ParentId>
    <Memo1>901</Memo1>
    <Memo2>55</Memo2>
    <Memo3>
    </Memo3>
  </CityItem>
  <CityItem>
    <CityId>906</CityId>
    <CityName>廊坊</CityName>
    <EngName>langfang</EngName>
    <Level>4</Level>
    <ParentId>9</ParentId>
    <Memo1>901</Memo1>
    <Memo2>54</Memo2>
    <Memo3>
    </Memo3>
  </CityItem>
  <CityItem>
    <CityId>1102</CityId>
    <CityName>大庆</CityName>
    <EngName>daqing</EngName>
    <Level>2</Level>
    <ParentId>11</ParentId>
    <Memo1>1101</Memo1>
    <Memo2>71</Memo2>
    <Memo3>
    </Memo3>
  </CityItem>
  <CityItem>
    <CityId>1710</CityId>
    <CityName>鞍山</CityName>
    <EngName>anshan</EngName>
    <Level>4</Level>
    <ParentId>17</ParentId>
    <Memo1>1701</Memo1>
    <Memo2>67</Memo2>
    <Memo3>
    </Memo3>
  </CityItem>
  <CityItem>
    <CityId>1808</CityId>
    <CityName>鄂尔多斯</CityName>
    <EngName>eerduosi</EngName>
    <Level>4</Level>
    <ParentId>18</ParentId>
    <Memo1>1801</Memo1>
    <Memo2>31</Memo2>
    <Memo3>
    </Memo3>
  </CityItem>
  <CityItem>
    <CityId>1802</CityId>
    <CityName>包头</CityName>
    <EngName>baotou</EngName>
    <Level>4</Level>
    <ParentId>18</ParentId>
    <Memo1>1801</Memo1>
    <Memo2>30</Memo2>
    <Memo3>
    </Memo3>
  </CityItem>
  <CityItem>
    <CityId>2107</CityId>
    <CityName>枣庄</CityName>
    <EngName>zaozhuang</EngName>
    <Level>5</Level>
    <ParentId>21</ParentId>
    <Memo1>2101</Memo1>
    <Memo2>42</Memo2>
    <Memo3>
    </Memo3>
  </CityItem>
  <CityItem>
    <CityId>2120</CityId>
    <CityName>日照</CityName>
    <EngName>rizhao</EngName>
    <Level>4</Level>
    <ParentId>21</ParentId>
    <Memo1>2102</Memo1>
    <Memo2>48</Memo2>
    <Memo3>
    </Memo3>
  </CityItem>
  <CityItem>
    <CityId>2118</CityId>
    <CityName>济宁</CityName>
    <EngName>jining</EngName>
    <Level>3</Level>
    <ParentId>21</ParentId>
    <Memo1>2101</Memo1>
    <Memo2>36</Memo2>
    <Memo3>
    </Memo3>
  </CityItem>
  <CityItem>
    <CityId>1015</CityId>
    <CityName>德州</CityName>
    <EngName>dezhou</EngName>
    <Level>4</Level>
    <ParentId>21</ParentId>
    <Memo1>2101</Memo1>
    <Memo2>40</Memo2>
    <Memo3>
    </Memo3>
  </CityItem>
  <CityItem>
    <CityId>2106</CityId>
    <CityName>泰安</CityName>
    <EngName>taian</EngName>
    <Level>4</Level>
    <ParentId>21</ParentId>
    <Memo1>2101</Memo1>
    <Memo2>38</Memo2>
    <Memo3>
    </Memo3>
  </CityItem>
  <CityItem>
    <CityId>2110</CityId>
    <CityName>东营</CityName>
    <EngName>dongying</EngName>
    <Level>3</Level>
    <ParentId>21</ParentId>
    <Memo1>2101</Memo1>
    <Memo2>37</Memo2>
    <Memo3>
    </Memo3>
  </CityItem>
  <CityItem>
    <CityId>2113</CityId>
    <CityName>滨州</CityName>
    <EngName>binzhou</EngName>
    <Level>4</Level>
    <ParentId>21</ParentId>
    <Memo1>2101</Memo1>
    <Memo2>39</Memo2>
    <Memo3>
    </Memo3>
  </CityItem>
  <CityItem>
    <CityId>2104</CityId>
    <CityName>威海</CityName>
    <EngName>weihai</EngName>
    <Level>4</Level>
    <ParentId>21</ParentId>
    <Memo1>2102</Memo1>
    <Memo2>47</Memo2>
    <Memo3>
    </Memo3>
  </CityItem>
  <CityItem>
    <CityId>2205</CityId>
    <CityName>临汾</CityName>
    <EngName>linfen</EngName>
    <Level>4</Level>
    <ParentId>22</ParentId>
    <Memo1>2201</Memo1>
    <Memo2>59</Memo2>
    <Memo3>
    </Memo3>
  </CityItem>
  <CityItem>
    <CityId>1014</CityId>
    <CityName>安阳</CityName>
    <EngName>anyang</EngName>
    <Level>4</Level>
    <ParentId>10</ParentId>
    <Memo1>1001</Memo1>
    <Memo2>128</Memo2>
    <Memo3>
    </Memo3>
  </CityItem>
  <CityItem>
    <CityId>1009</CityId>
    <CityName>南阳</CityName>
    <EngName>nanyang</EngName>
    <Level>4</Level>
    <ParentId>10</ParentId>
    <Memo1>1001</Memo1>
    <Memo2>127</Memo2>
    <Memo3>
    </Memo3>
  </CityItem>
  <CityItem>
    <CityId>1207</CityId>
    <CityName>宜昌</CityName>
    <EngName>yichang</EngName>
    <Level>2</Level>
    <ParentId>12</ParentId>
    <Memo1>1201</Memo1>
    <Memo2>119</Memo2>
    <Memo3>
    </Memo3>
  </CityItem>
  <CityItem>
    <CityId>1302</CityId>
    <CityName>郴州</CityName>
    <EngName>chenzhou</EngName>
    <Level>5</Level>
    <ParentId>13</ParentId>
    <Memo1>1301</Memo1>
    <Memo2>134</Memo2>
    <Memo3>
    </Memo3>
  </CityItem>
  <CityItem>
    <CityId>507</CityId>
    <CityName>汕头</CityName>
    <EngName>shantou</EngName>
    <Level>5</Level>
    <ParentId>5</ParentId>
    <Memo1>502</Memo1>
    <Memo2>108</Memo2>
    <Memo3>
    </Memo3>
  </CityItem>
  <CityItem>
    <CityId>520</CityId>
    <CityName>惠州</CityName>
    <EngName>huizhou</EngName>
    <Level>4</Level>
    <ParentId>5</ParentId>
    <Memo1>502</Memo1>
    <Memo2>105</Memo2>
    <Memo3>
    </Memo3>
  </CityItem>
  <CityItem>
    <CityId>503</CityId>
    <CityName>珠海</CityName>
    <EngName>zhuhai</EngName>
    <Level>4</Level>
    <ParentId>5</ParentId>
    <Memo1>502</Memo1>
    <Memo2>103</Memo2>
    <Memo3>
    </Memo3>
  </CityItem>
  <CityItem>
    <CityId>603</CityId>
    <CityName>桂林</CityName>
    <EngName>guilin</EngName>
    <Level>5</Level>
    <ParentId>6</ParentId>
    <Memo1>601</Memo1>
    <Memo2>118</Memo2>
    <Memo3>
    </Memo3>
  </CityItem>
  <CityItem>
    <CityId>303</CityId>
    <CityName>龙岩</CityName>
    <EngName>longyan</EngName>
    <Level>4</Level>
    <ParentId>3</ParentId>
    <Memo1>301</Memo1>
    <Memo2>99</Memo2>
    <Memo3>
    </Memo3>
  </CityItem>
  <CityItem>
    <CityId>3011</CityId>
    <CityName>湖州</CityName>
    <EngName>huzhou</EngName>
    <Level>4</Level>
    <ParentId>30</ParentId>
    <Memo1>3002</Memo1>
    <Memo2>94</Memo2>
    <Memo3>
    </Memo3>
  </CityItem>
  <CityItem>
    <CityId>3005</CityId>
    <CityName>嘉兴</CityName>
    <EngName>jiaxing</EngName>
    <Level>3</Level>
    <ParentId>30</ParentId>
    <Memo1>3001</Memo1>
    <Memo2>92</Memo2>
    <Memo3>
    </Memo3>
  </CityItem>
  <CityItem>
    <CityId>1504</CityId>
    <CityName>常熟</CityName>
    <EngName>changshu</EngName>
    <Level>0</Level>
    <ParentId>15</ParentId>
    <Memo1>1502</Memo1>
    <Memo2>167</Memo2>
    <Memo3>15</Memo3>
  </CityItem>
  <CityItem>
    <CityId>1515</CityId>
    <CityName>镇江</CityName>
    <EngName>zhenjiang</EngName>
    <Level>4</Level>
    <ParentId>15</ParentId>
    <Memo1>1501</Memo1>
    <Memo2>83</Memo2>
    <Memo3>
    </Memo3>
  </CityItem>
  <CityItem>
    <CityId>1513</CityId>
    <CityName>扬州</CityName>
    <EngName>yangzhou</EngName>
    <Level>4</Level>
    <ParentId>15</ParentId>
    <Memo1>1501</Memo1>
    <Memo2>82</Memo2>
    <Memo3>
    </Memo3>
  </CityItem>
  <CityItem>
    <CityId>1517</CityId>
    <CityName>泰州</CityName>
    <EngName>taizhou</EngName>
    <Level>4</Level>
    <ParentId>15</ParentId>
    <Memo1>1502</Memo1>
    <Memo2>86</Memo2>
    <Memo3>
    </Memo3>
  </CityItem>
  <CityItem>
    <CityId>2001</CityId>
    <CityName>西宁</CityName>
    <EngName>xining</EngName>
    <Level>5</Level>
    <ParentId>20</ParentId>
    <Memo1>401</Memo1>
    <Memo2>151</Memo2>
    <Memo3>
    </Memo3>
  </CityItem>
  <CityItem>
    <CityId>2502</CityId>
    <CityName>绵阳</CityName>
    <EngName>mianyang</EngName>
    <Level>5</Level>
    <ParentId>25</ParentId>
    <Memo1>2501</Memo1>
    <Memo2>139</Memo2>
    <Memo3>
    </Memo3>
  </CityItem>
  <CityItem>
    <CityId>2701</CityId>
    <CityName>拉萨</CityName>
    <EngName>lasa</EngName>
    <Level>5</Level>
    <ParentId>27</ParentId>
    <Memo1>2501</Memo1>
    <Memo2>142</Memo2>
    <Memo3>
    </Memo3>
  </CityItem>
</CityValueSet>